{
  "country": "Panamá",
  "name_note": "⭐ Puntuación de expatriados: 7.0 / 10",
  "expat_score": {
    "value": 7.0,
    "max": 10,
    "label": "⭐ Puntuación de expatriados: 7.0 / 10"
  },
  "snapshot": {
    "capital": "Ciudad de Panamá",
    "population": "~4.4M",
    "languages": "español, inglés",
    "driving_side": "Derecha"
  },
  "currency": {
    "name": "Dólar estadounidense (USD) / balboa panameño (PAB)",
    "rate": "1 USD = 1 PAB",
    "note": "Utiliza el dólar estadounidense como moneda oficial (desde 1904). Sin riesgo de tipo de cambio. Existen monedas en balboa pero circulan billetes en dólares."
  },
  "crypto": {
    "friendly": "Sí",
    "note": "Amigable con las criptomonedas. La ley reconoce las cripto (2021). Adopción en crecimiento. La cercanía a El Salvador influyó en políticas. Se están desarrollando regulaciones claras."
  },
  "article": "🧭 **Resumen**\nPanamá es un país de Centroamérica que conecta Norte y Suramérica, conocido por el Canal de Panamá (maravilla de la ingeniería, fuente importante de ingresos), el sector bancario (centro financiero regional) y su biodiversidad. Ciudad de Panamá es la capital moderna con un skyline tipo Manhattan; Casco Viejo es el barrio colonial. El país ofrece una economía en dólares estadounidenses, un sistema fiscal favorable, programas para jubilados (visa de Pensionado) y una ubicación estratégica. La economía depende del Canal, la banca, la logística y los servicios. Panamá atrae a expatriados y jubilados que buscan un estilo de vida tropical con la estabilidad del dólar. Sin embargo, la desigualdad, la corrupción (Papeles de Panamá 2016), la delincuencia, la temporada de lluvias y el tráfico generan desafíos. Es la potencia económica de Centroamérica.\n\n👥 **Gente y ambiente**\nCon aproximadamente 4.4 millones de personas, Panamá es étnicamente diversa: mestiza (~65%), negra/afro-panamense (~15%), blanca (~10%), indígena (~7%). El español es oficial; se habla inglés (especialmente en negocios, legado de la Zona del Canal). La cultura es latinoamericana con influencias caribeñas y norteamericanas. Los panameños son amables, emprendedores y diversos. El ambiente es de trópico cosmopolita. Ciudad de Panamá es un centro financiero moderno; Casco Viejo está en pleno renacimiento hipster; Bocas del Toro es un refugio de playa para expatriados; el interior es rural. La desigualdad es visible.\n\n[[MAP]]\n\n🌦️ **Clima y paisaje**\nEspere un clima tropical: caliente y húmedo todo el año (25-32°C) con temporada de lluvias (may-oct, chaparrones fuertes por la tarde) y temporada seca (dic-abr). El paisaje incluye dos costas (Pacífico y Caribe), montañas (las tierras altas son más frescas — Boquete, El Valle), selvas tropicales (Darién es jungla densa) e islas (San Blas, Bocas del Toro). La belleza natural es accesible. La biodiversidad es excepcional. La calidad del aire es moderada.\n\n🏠 **Vivienda e instalarse**\nCiudad de Panamá (Punta Pacífica, Costa del Este, Casco Viejo) atrae a expatriados; Boquete (tierras altas) y Bocas del Toro (islas) son populares. Espere depósito de 1-2 meses y contratos anuales. Alquileres: $800-2,000+/mes en la ciudad; $400-800 en Boquete. La calidad es buena — rascacielos modernos en la ciudad, casas en otras zonas. El aire acondicionado es esencial. Fuera de las áreas principales, las opciones son limitadas. Comprar propiedad es sencillo para extranjeros (sin restricciones). Se requiere registración. Las inundaciones en temporada de lluvias pueden ser un problema.\n\n💼 **Trabajo y economía**\nLa economía está impulsada por los servicios: el Canal (genera $2.5B+ en ingresos), la banca (centro financiero regional), la logística (Zona Libre de Colón) y el turismo. Para extranjeros, hay oportunidades en banca, logística, tecnología (escena startup en crecimiento), turismo o enseñanza de inglés. Los permisos de trabajo requieren patrocinio por parte del empleador. El programa de Pensionado atrae jubilados. Los salarios varían: los expatriados ganan bien ($3k-8k/mes); los locales ganan menos. Montar un negocio es relativamente fácil. La prevalencia del inglés (banca, legado del Canal) ayuda. El sistema de impuesto territorial (solo se grava la renta generada en Panamá) atrae a empresas.\n\n🛂 **Visados y entrada**\nLa mayoría de las nacionalidades recibe una visa de turista de 180 días a la llegada. Para estancias más largas, las opciones incluyen la visa de las Naciones Amigas (ciudadanos de 50 países pueden obtener residencia con inversión de $5k), la visa de Pensionado (jubilados con pensión de $1k/mes obtienen descuentos) o permisos de trabajo. El proceso es burocrático pero accesible. La residencia permanente lleva a la elegibilidad para la ciudadanía después de 5 años. La naturalización es posible — requiere dominio del español.\n\n🏥 **Salud**\nLa atención sanitaria es de doble nivel. El sistema público (CSS) es económico pero concurrido. Los hospitales privados (Hospital Punta Pacífica, afiliado a Johns Hopkins) ofrecen atención excelente a precios razonables. El turismo médico atrae a norteamericanos (odontología, cirugía estética, procedimientos). La esperanza de vida es ~79 años. Se recomienda seguro internacional o seguro privado. Los medicamentos con receta son asequibles. La calidad en Ciudad de Panamá es buena; en zonas rurales la atención es básica.\n\n🚗 **Transporte y movilidad**\nCiudad de Panamá tiene metro (2 líneas, en expansión), buses y Uber. El tráfico es terrible — congestión, conducción agresiva. La mayoría de expatriados conduce o usa Uber. Las carreteras en las ciudades son decentes; la Carretera Panamericana conecta el interior. El Tapón del Darién (sin carretera entre Panamá y Colombia — jungla) es notorio. Vuelos domésticos conectan el interior y las islas. El Aeropuerto Internacional de Tocumen es un gran hub para Latinoamérica. Viajar por la región es fácil.\n\n🍛 **Nota sobre la comida (plato nacional)**\nEl plato nacional es el **Sancocho**: sopa de pollo con yuca, maíz, plátano y cilantro. Es comida reconfortante que se sirve en reuniones familiares. Alternativamente, **Ceviche** o **Ropa Vieja** (carne deshebrada). La cocina panameña es latinoamericana con influencias caribeñas. Los mariscos son excelentes. La comida internacional está ampliamente disponible en Ciudad de Panamá.\n\n🔎 **Conclusión**\nPanamá conviene a jubilados (el programa de Pensionado ofrece descuentos), nómadas digitales, expatriados que buscan Latinoamérica con la estabilidad del dólar, familias e inversores. Pros: dólar estadounidense (sin riesgo cambiario), ingresos del Canal que generan riqueza, centro bancario, ubicación estratégica, biodiversidad, programas de Visa de las Naciones Amigas y Pensionado, e infraestructura en mejora. Contras: desigualdad (notoria), corrupción (los Papeles de Panamá expusieron la industria offshore), delincuencia (especialmente en Ciudad de Panamá), caos de tráfico, temporada de lluvias (6+ meses) y clima cálido/húmedo. Ciudad de Panamá es moderna pero congestionada; Boquete ofrece escape montañoso; las playas atraen turistas. Es ideal para quienes buscan un estilo de vida tropical en Latinoamérica con la estabilidad del dólar y están dispuestos a aceptar desigualdad y corrupción. El español es esencial para integrarse. Si quiere la economía más desarrollada de Centroamérica con montañas, playas y sin riesgo cambiario, Panamá cumple.\n\nPuntuación de expatriados — 7.0 / 10",
  "goDeeper": {
    "national_dish": {
      "name": "Sancocho / Ceviche",
      "note": "Sopa de pollo con yuca o ceviche — cocina latinoamericana/caribeña. Los mariscos son excelentes. La comida internacional está ampliamente disponible."
    },
    "lgbt_acceptance": {
      "level": "Moderado",
      "note": "La homosexualidad es legal. Las actitudes sociales están mejorando, especialmente en Ciudad de Panamá. No hay matrimonio entre personas del mismo sexo pero existen algunas protecciones. Ciudad de Panamá tiene una escena LGBTI+. Es más tolerante que algunos países vecinos."
    },
    "top_sectors": [
      "Operaciones del Canal de Panamá",
      "Banca y servicios financieros",
      "Logística y zona de libre comercio"
    ],
    "things_to_know": {
      "personality": {
        "name": "Omar Torrijos",
        "era": "Siglo XX",
        "story": "Líder militar (1968-81) que negoció los Tratados Torrijos-Carter (1977) para transferir el Canal de EE. UU. a Panamá (completado en 1999). Dictador populista que mejoró la infraestructura rural. Murió en un accidente aéreo (1981). Héroe nacional por la soberanía del Canal."
      },
      "cards": [
        {
          "title": "🚢 Canal de Panamá = salvavidas económico",
          "text": "Conecta el Atlántico con el Pacífico, maneja el 6% del comercio mundial. Genera más de $2.5B en ingresos anuales. Ampliado en 2016 para manejar barcos Neopanamax. Es la base económica y orgullo nacional. EE. UU. controló 1904-99; Panamá asumió el control. Los ingresos financian desarrollo."
        },
        {
          "title": "💼 Papeles de Panamá (2016) = capital offshore",
          "text": "Una filtración masiva expuso la industria bancaria offshore de Panamá — sociedades pantalla, evasión fiscal, blanqueo de capitales para la élite global. El bufete Mossack Fonseca fue el centro. Confirmó el papel de Panamá como jurisdicción de secreto financiero. La reputación resultó dañada pero la industria continúa."
        },
        {
          "title": "🏖️ Bocas del Toro = vida insular de expatriados",
          "text": "Islas caribeñas con playas, buceo y ambiente reggae. Populares entre mochileros, expatriados y jubilados. El costo de vida es más bajo que en la ciudad. Sin embargo, la presión turística y la sobreurbanización amenazan su carácter. Los cortes de energía y problemas de agua son comunes. Es un escape tropical relajado."
        },
        {
          "title": "🏔️ Boquete = paraíso montañoso para jubilados",
          "text": "Pueblo de tierras altas (1.200 m de altitud) con clima de eterna primavera, fincas de café y una gran comunidad de expatriados (especialmente jubilados norteamericanos). La visa de Pensionado ofrece descuentos (25% en restaurantes, 50% en entretenimiento). Es el principal destino de expatriados de Panamá fuera de la ciudad."
        },
        {
          "title": "🌳 Tapón del Darién = jungla impenetrable",
          "text": "100 km de jungla sin carreteras entre Panamá y Colombia — el único corte en la Carretera Panamericana (Alaska a Argentina). Selva densa, pantanos, peligroso. Migrantes que intentan llegar a EE. UU. la atraviesan (muchos mueren). Es una de las selvas más peligrosas del mundo. Sin infraestructura."
        },
        {
          "title": "💵 Economía en USD = estabilidad",
          "text": "Panamá usa el dólar estadounidense desde 1904 (sin banco central, sin política monetaria propia). Esto crea estabilidad de precios, atrae inversión, pero también significa incapacidad para devaluar en crisis. Es inusual fuera de un territorio estadounidense. El dólar es a la vez beneficio y limitación."
        }
      ]
    }
  }
}