{
  "country": "Botswana",
  "name_note": "⭐ Score Expat : 6,5 / 10",
  "expat_score": {
    "value": 6.5,
    "max": 10,
    "label": "⭐ Score Expat : 6,5 / 10"
  },
  "snapshot": {
    "capital": "Gaborone",
    "population": "~2,6M",
    "languages": "Anglais, Setswana",
    "driving_side": "Gauche"
  },
  "currency": {
    "name": "Pula du Botswana (BWP)",
    "rate": "1 USD ≈ 13,50 BWP",
    "note": "Monnaie stable. Une économie bien gérée inspire confiance dans la devise."
  },
  "crypto": {
    "friendly": "Limitée",
    "note": "Aucune réglementation spécifique. Petite communauté crypto. Système bancaire traditionnel. Statut juridique peu clair."
  },
  "article": "🧭 **Aperçu**\nLe Botswana est une réussite d'Afrique australe sans accès à la mer — démocratie stable, gestion prudente des ressources et croissance régulière depuis l'indépendance (1966). Le désert du Kalahari couvre ~70 % du pays, entraînant une faible densité de population. Les diamants financent l'économie (le Botswana est le premier producteur mondial en valeur), permettant des investissements dans les infrastructures et les services. Gaborone, la capitale, est ordonnée et en expansion. Le pays accorde une grande importance à la conservation — 40 % des terres sont protégées, y compris le delta de l'Okavango, l'un des plus grands spectacles animaliers d'Afrique. Le Botswana est sûr, bien gouverné et devient de plus en plus un pays à revenu intermédiaire.\n\n👥 **Population et ambiance**\nAvec environ 2,6 millions d'habitants, la population du Botswana est majoritairement d'ethnie tswana avec des minorités (Kalanga, Basarwa/San). L'anglais est la langue officielle et largement parlée ; le setswana est la langue nationale. La culture valorise le respect, la courtoisie (botho — similaire à l'Ubuntu) et le consensus communautaire. Les gens sont en général amicaux, polis et réservés. Gaborone est cosmopolite et en croissance ; les zones rurales restent traditionnelles. Le christianisme est dominant. Le rythme de vie est modéré — ni frénétique ni endormi. Les taux de VIH/sida ont été historiquement très élevés mais une réponse gouvernementale agressive a inversé la tendance.\n\n[[MAP]]\n\n🌦️ **Climat et paysage**\nAttendez-vous à un climat semi-aride : étés chauds (octobre-avril, 25-35°C) avec pluies occasionnelles (surtout décembre-mars), et hivers chauds et secs (mai-septembre, journées 20-25°C, nuits fraîches). Le désert du Kalahari domine — pas un Sahara de dunes mais une steppe arbustive à végétation clairsemée. Le delta de l'Okavango au nord-ouest est une oasis humide regorgeant de faune. Les régions nord (Chobe, Moremi) offrent des safaris de premier ordre. Le Botswana est plat avec peu de variations géographiques. La qualité de l'air est généralement bonne.\n\n🏠 **Logement et installation**\nLe marché locatif de Gaborone propose appartements, maisons en rangée et maisons individuelles. Les quartiers populaires incluent Phakalane, Gaborone West et le centre-ville. Prévoyez 1-2 mois de dépôt de garantie et des baux de 6 à 12 mois. Les loyers sont modérés (400 à 1 200 USD/mois selon la qualité). Les standards de logement sont corrects avec des équipements modernes. Les complexes fermés et lotissements sécurisés sont courants. L'électricité est fiable. Des coupures d'eau peuvent survenir occasionnellement. En dehors de Gaborone, des villes comme Francistown et Maun offrent des options limitées. L'enregistrement auprès de l'immigration est obligatoire.\n\n💼 **Travail et économie**\nL'économie est tirée par les diamants (De Beers), avec des secteurs en croissance dans le tourisme, les services financiers et la fabrication. Pour les étrangers, des opportunités existent dans l'exploitation minière, la conservation/tourisme, l'éducation, la santé et les ONG. Les permis de travail exigent le parrainage d'un employeur et la preuve qu'aucun citoyen qualifié n'est disponible — le gouvernement privilégie l'emploi local (politique de localisation). Les salaires sont compétitifs pour la région mais inférieurs à ceux des pays occidentaux. Le chômage des citoyens est d'environ 20 %+. Créer une entreprise est possible mais nécessite souvent des partenariats locaux. La prévalence de l'anglais est un avantage.\n\n🛂 **Visa et entrée**\nDe nombreuses nationalités (y compris États-Unis, UE, Royaume-Uni, Commonwealth) peuvent entrer sans visa pour 90 jours. Pour des séjours plus longs, les permis de travail requièrent le parrainage d'un employeur et une documentation étendue incluant casiers judiciaires, examens médicaux et preuves de qualifications. Le processus est bureaucratique mais plus transparent que dans de nombreux pays africains. Les permis de résidence sont liés au travail. La résidence permanente demande des années de présence continue. La citoyenneté est difficile et nécessite plus de 10 ans, ainsi que l'abandon possible d'autres nationalités.\n\n🏥 **Soins de santé**\nLe système de santé comprend des structures publiques et privées. Les établissements publics sont gratuits/peu coûteux mais surchargés et sous-équipés. Les hôpitaux privés à Gaborone (Marina Hospital, Bokamoso) offrent une bonne qualité à coût raisonnable. Les cas graves peuvent nécessiter une évacuation vers l'Afrique du Sud. Le tourisme médical vers l'AFS est courant. Le traitement du VIH/sida est gratuit et de grande qualité grâce aux programmes gouvernementaux. L'espérance de vie a augmenté à ~70 ans après que la crise liée au VIH l'ait fait chuter à ~40 au début des années 2000. Une assurance santé internationale est recommandée.\n\n🚗 **Transports et mobilité**\nGaborone dispose d'un transport public limité — des minibus (combis) desservent les zones urbaines mais sont peu fiables. La plupart des gens conduisent. Les routes en ville sont en bon état ; les routes rurales varient. On conduit à gauche, et les traversées d'animaux sauvages constituent un risque réel hors des villes. Des bus interurbains relient les villes à moindre coût. Le pays est vaste et peu peuplé — les distances sont importantes. Des vols domestiques existent mais sont coûteux. L'aéroport international Sir Seretse Khama à Gaborone est connecté à Johannesburg, Addis-Abeba et d'autres destinations régionales. La plupart des voyages internationaux passent par Johannesburg.\n\n🍛 **Note culinaire (plat national)**\nLe plat national est **Seswaa** : viande de bœuf ou de chèvre lentement mijotée et effilochée, traditionnellement pilée dans un mortier. Il est servi avec du pap (bouillie de maïs) et constitue un aliment de base lors des célébrations et rassemblements. La préparation est communautaire et chronophage, reflétant la culture culinaire traditionnelle et l'hospitalité.\n\n🔎 **En bref**\nLe Botswana convient aux professionnels de la conservation, aux travailleurs du secteur minier, aux rôles d'entreprise régionale, ou à ceux cherchant une expérience africaine avec une gouvernance et une sécurité meilleures que la plupart des alternatives. La stabilité, la langue anglaise, la beauté naturelle (le delta de l'Okavango est de classe mondiale) et une économie en croissance sont des attraits majeurs. Cependant, des coûts de la vie élevés par rapport à l'économie locale, un marché de l'emploi limité pour les étrangers, l'éloignement, l'héritage du VIH (même s'il s'améliore) et un climat désertique difficile posent des défis. C'est une Afrique édulcorée — plus sûre, plus ordonnée, mais moins bouillonnante que certains voisins. Idéal pour des secteurs spécifiques ou pour ceux privilégiant la stabilité à l'effervescence.\n\nScore Expat — 6,5 / 10",
  "goDeeper": {
    "national_dish": {
      "name": "Seswaa",
      "note": "Viande de bœuf ou de chèvre lentement mijotée et effilochée, pilée au mortier, servie avec du pap — plat traditionnel et communautaire central lors des célébrations."
    },
    "lgbt_acceptance": {
      "level": "Faible",
      "note": "L'homosexualité a été décriminalisée en 2019 (progrès majeur) mais les attitudes sociales restent conservatrices. La discrimination est courante. La discrétion est conseillée malgré les avancées juridiques."
    },
    "top_sectors": [
      "Extraction et transformation du diamant",
      "Tourisme et conservation",
      "Services financiers"
    ],
    "things_to_know": {
      "personality": {
        "name": "Sir Seretse Khama",
        "era": "20e siècle",
        "story": "Président fondateur qui a conduit le Botswana du protectorat britannique à l'indépendance (1966). Son mariage interracial avec une Britannique provoqua un scandale à l'époque de l'apartheid en Afrique australe. Il a gouverné avec sagesse, posant les bases de la stabilité et de la prospérité du Botswana. Héros national et modèle de dirigeant."
      },
      "cards": [
        {
          "title": "💎 Diamonds = development done right",
          "text": "Contrairement aux nations maudites par les ressources, le Botswana a investi les revenus du diamant de façon judicieuse dans les infrastructures, l'éducation et la santé. Le partenariat avec De Beers repose sur le partage des profits, pas sur l'exploitation. C'est un exemple rare où la richesse des ressources a créé une prospérité large, bien que les inégalités persistent."
        },
        {
          "title": "🦁 Okavango Delta = natural wonder",
          "text": "Plus grand delta intérieur du monde, site classé par l'UNESCO où la rivière Okavango disparaît dans le Kalahari. Les inondations saisonnières créent une oasis peuplée d'éléphants, de lions, d'hippopotames et d'oiseaux. Des camps de safari de luxe offrent des expériences animalières de classe mondiale. C'est l'Éden africain."
        },
        {
          "title": "🇿🇦 South Africa's shadow",
          "text": "Le Botswana est économiquement et géographiquement lié à l'Afrique du Sud. La plupart des importations transitent par l'AFS. Johannesburg est le hub régional. Le pula est lié de manière indirecte au rand. Quand l'AFS éternue, le Botswana attrape froid. Pourtant le Botswana a maintenu sa stabilité tandis que l'AFS a peiné avec l'apartheid et la transition."
        },
        {
          "title": "🩺 HIV success story",
          "text": "Le Botswana a affiché la prévalence de VIH la plus élevée au monde (~25-30 % de la population adulte). Une réponse gouvernementale agressive avec traitement antirétroviral gratuit, campagnes de dépistage et prévention a inversé la tendance. L'espérance de vie est passée d'environ 40 à 70 ans. C'est un modèle de prise en charge du VIH."
        },
        {
          "title": "🏛️ Democracy in action",
          "text": "Le Botswana est l'une des démocraties les plus stables d'Afrique avec des transitions de pouvoir pacifiques depuis l'indépendance. La liberté de la presse existe. La corruption est faible selon les normes régionales. Les tribunaux sont indépendants. Ce n'est pas parfait mais remarquablement fonctionnel comparé aux voisins."
        },
        {
          "title": "💧 Water scarcity is real",
          "text": "Malgré le delta de l'Okavango, la majeure partie du pays est désertique. L'eau est précieuse et coûteuse. Les sécheresses sont fréquentes. Le changement climatique menace l'avenir. Les infrastructures et la conservation de l'eau sont des priorités nationales. On ne peut pas s'attendre à une abondance d'eau."
        }
      ]
    }
  }
}