{
  "country": "Roumanie",
  "name_note": "⭐ Score des expatriés : 7.0 / 10",
  "expat_score": {
    "value": 7.0,
    "max": 10,
    "label": "⭐ Score des expatriés : 7.0 / 10"
  },
  "snapshot": {
    "capital": "Bucarest",
    "population": "~19M",
    "languages": "Roumain, anglais",
    "driving_side": "Conduite à droite"
  },
  "currency": {
    "name": "Leu roumain (RON)",
    "rate": "1 USD ≈ 4.60 RON",
    "note": "Monnaie relativement stable. La Roumanie n'est pas encore dans la zone euro, mais une adoption éventuelle est prévue."
  },
  "crypto": {
    "friendly": "Oui",
    "note": "Favorable aux cryptos avec une fiscalité claire. Les plus-values sont taxées à un taux forfaitaire de 10 %. Communauté blockchain en croissance."
  },
  "article": "🧭 **Aperçu**\nLa Roumanie est une nation d'Europe de l'Est offrant la Transylvanie (légende de Dracula), les Carpates, la côte de la mer Noire, des villes médiévales (Brașov, Sibiu), et un coût de la vie abordable. Bucarest est la capitale surnommée « Petit Paris » (époque pré-communiste). Le pays est passé avec succès de la brutale dictature de Ceaușescu (1965-89, exécuté lors de la révolution) à membre de l'UE (2007). L'économie repose sur l'industrie manufacturière, l'externalisation informatique, l'agriculture et le tourisme. La Roumanie offre des coûts faibles, un Internet rapide (parmi les plus rapides au monde), la nature et des infrastructures en amélioration. Cependant, la corruption (endémique), la fuite des cerveaux (émigration massive vers l'Europe de l'Ouest), des lacunes d'infrastructures (surtout en zone rurale) et les problèmes de chiens errants posent des défis.\n\n👥 **Population & ambiance**\nAvec environ 19 millions d'habitants (en baisse depuis 23M en 1990 à cause de l'émigration), la Roumanie est ethniquement roumaine (~83 %), hongroise (~6 %, en Transylvanie), rom (~3 % officiellement, probablement plus). Le roumain est une langue romane (dérivée du latin, plus proche de l'italien/espagnol que des voisins slaves). L'anglais est parlé par les jeunes. Le christianisme orthodoxe domine. La culture met l'accent sur l'hospitalité, la superstition (mauvais œil, ail), la résilience et un certain fatalisme façonné par le traumatisme communiste. Les Roumains sont chaleureux mais pessimistes. L'ambiance est celle d'un entre-deux post-communiste. Bucarest est chaotique ; la Transylvanie est pittoresque ; la mer Noire attire le tourisme balnéaire. Le tourisme lié à Dracula est une industrie malgré le fait que Vlad l'Empaleur soit valaques et non transylvain.\n\n[[MAP]]\n\n🌦️ **Climat & paysage**\nAttendez-vous à un climat continental : étés chauds (25-35°C), hivers froids (-5 à 5°C avec neige), printemps/automnes agréables. Le paysage comprend les Carpates (ski, randonnées), le Danube et son delta (UNESCO, ornithologie), la côte de la mer Noire, les collines de Transylvanie et les plaines. La beauté naturelle est accessible et sous-estimée. La qualité de l'air est moyenne ; Bucarest connaît de la pollution.\n\n🏠 **Logement & installation**\nBucarest (Pipera, Aviatorilor, centre historique) attire les expatriés ; Cluj-Napoca, Brașov, Timișoara ont des communautés en croissance. Prévoir 1 à 2 mois de dépôt de garantie et des contrats annuels. Les loyers sont bas : Bucarest RON 1 500–3 500/mois ($325-760) ; Cluj RON 1 200–2 500. La qualité varie — les immeubles rénovés sont agréables ; les blocs de l'époque communiste sont austères mais bon marché. Le chauffage est essentiel (chauffage urbain ou individuel). L'enregistrement est requis. L'achat de biens immobiliers est autorisé. En dehors des villes, les zones rurales sont très bon marché mais les infrastructures sont minimales.\n\n💼 **Travail & économie**\nL'économie repose sur la fabrication (automobile — Dacia/Renault), l'externalisation informatique (Cluj est le « Silicon Valley » roumain), l'agriculture et les services. Pour les citoyens de l'UE, la libre circulation s'applique. Les non-UE ont besoin de permis de travail. Des opportunités existent dans l'informatique, la finance, les centres de services partagés, l'enseignement de l'anglais ou les startups. Les salaires sont faibles par rapport aux standards occidentaux (RON 4 000–12 000/mois, $870-2 600) mais les coûts suivent. L'équilibre vie pro/vie perso s'améliore. L'anglais suffit dans l'informatique et les affaires. La fuite des cerveaux est sévère — plus de 5M de Roumains travaillent à l'étranger. La corruption affecte le monde des affaires.\n\n🛂 **Visa & entrée**\nLes citoyens UE/EEE/Suisse ont la libre circulation. Les non-UE peuvent visiter 90 jours sur 180 jours. Pour des séjours plus longs, les permis de travail nécessitent un parrainage employeur. Le processus est bureaucratique. La résidence permanente requiert 5 ans de résidence continue. La citoyenneté nécessite 8 ans de résidence (ou 5 si marié à un Roumain), une maîtrise du roumain (B2) et la réussite d'examens. La naturalisation est réalisable.\n\n🏥 **Santé**\nLe système de santé est universel mais la qualité est médiocre. Les hôpitaux publics sont surchargés, sous-équipés, et la corruption (șpagă — paiements informels aux médecins) est une norme culturelle. Les cliniques privées offrent de meilleurs soins à des tarifs abordables. Pour des affections graves, il peut être nécessaire de se rendre en Hongrie, en Allemagne ou en Autriche. L'espérance de vie est d'environ 75 ans. Une assurance internationale est recommandée. Les citoyens de l'UE peuvent utiliser la CEAM, mais les problèmes de qualité subsistent.\n\n🚗 **Transports & mobilité**\nBucarest dispose d'un métro (4 lignes), de bus et de trams — fonctionnels mais bondés. Les routes en ville sont pleines de nids-de-poule ; les autoroutes sont limitées mais en amélioration (financements UE). Le comportement au volant est agressif et chaotique. Les trains interurbains sont lents et vétustes ; les bus sont mieux. Le pays est de taille modérée — Bucarest à Brașov se fait en ~2,5 h en voiture. L'aéroport Henri Coandă (Bucarest) relie l'Europe. Les vols intérieurs sont rares.\n\n🍛 **Note sur la cuisine (plat national)**\nLe plat national est **Sarmale** : des feuilles de chou farcies de porc/boeuf et de riz, servies avec de la mămăligă (polenta) et de la crème aigre. Servi lors des célébrations. Autre spécialité : **Mici** (rouleaux de viande grillés). La cuisine roumaine est copieuse — porc, polenta, crème aigre, influencée par les traditions balkaniques, turques et hongroises. Le vin est correct et bon marché.\n\n🔎 **En résumé**\nLa Roumanie convient aux nomades numériques (Internet rapide, coûts bas), aux professionnels de l'informatique (scène tech de Cluj), aux voyageurs à petit budget et à ceux cherchant une base abordable dans l'UE. Avantages : très abordable, Internet rapide (parmi les plus rapides au monde), appartenance à l'UE, nature (Carpates, delta du Danube), villes médiévales (le charme de Brașov, Sibiu). Inconvénients : corruption (endémique, affecte la vie quotidienne), lacunes d'infrastructures (routes, zones rurales), fuite des cerveaux, chiens errants (surtout à Bucarest) et qualité des soins. Bucarest est bon marché mais chaotique ; la Transylvanie est pittoresque. Idéal pour ceux qui privilégient le faible coût et l'accès à l'UE plutôt que les infrastructures et la gouvernance. Le tourisme Dracula est kitsch mais le château de Bran tient la promesse. Si vous pouvez gérer la corruption, les nids-de-poule et accepter les réalités post-communistes, la Roumanie offre un excellent rapport qualité-prix.\n\nScore des expatriés — 7.0 / 10",
  "goDeeper": {
    "national_dish": {
      "name": "Sarmale / Mici",
      "note": "Roulades de chou ou rouleaux de viande grillés — cuisine copieuse à base de porc/polenta. Influences balkaniques/turques/hongroises. Le vin est bon marché."
    },
    "lgbt_acceptance": {
      "level": "Faible",
      "note": "L'homosexualité est légale mais il n'existe ni mariage ni unions civiles pour les couples de même sexe. Les attitudes sociales sont conservatrices. L'Église orthodoxe s'oppose aux droits LGBTQ+. La discrimination est courante. La discrétion est conseillée."
    },
    "top_sectors": [
      "Industrie automobile (Dacia)",
      "Externalisation informatique",
      "Agriculture"
    ],
    "things_to_know": {
      "personality": {
        "name": "Nicolae Ceaușescu",
        "era": "XXe siècle",
        "story": "Dictateur communiste (1965-89) dont la mégalomanie a ruiné le pays (construction du gigantesque Palais du Parlement, démolition du Vieux Bucarest). Securitate, police secrète brutale. La révolution de 1989 l'a renversé et exécuté. Son héritage est un traumatisme et le Palais (2e plus grand bâtiment du monde)."
      },
      "cards": [
        {
          "title": "🧛 Le tourisme Dracula = une industrie",
          "text": "Le château de Bran est commercialisé comme « château de Dracula » bien que Vlad l'Empaleur (inspiration pour Dracula) n'ait qu'un lien ténu. Bram Stoker n'a jamais visité la Roumanie. Mais l'industrie touristique a adopté le mythe. La Transylvanie joue la carte du kitsch vampirique. C'est une fiction rentable."
        },
        {
          "title": "📶 Internet parmi les plus rapides au monde",
          "text": "La Roumanie a des vitesses moyennes d'Internet parmi les plus élevées au monde (260+ Mbps). Héritage d'infrastructures post-communistes — des entreprises ont construit des réseaux fibre optique ex nihilo. Coûts ≈ 10 €/mois pour le gigabit. Paradoxe d'infrastructure tech — excellent Internet, routes médiocres."
        },
        {
          "title": "💰 Corruption = réalité quotidienne",
          "text": "Transparency International classe la Roumanie parmi les pays les plus corrompus de l'UE. Les pots-de-vin (șpagă) pour les médecins, les permis, la police sont une norme culturelle. Les campagnes anti-corruption ont emprisonné des politiciens mais le problème perdure. L'agence anticorruption (DNA) a été affaiblie. Cela affecte tout."
        },
        {
          "title": "🏛️ Le Palais du Parlement = mégalomanie communiste",
          "text": "2e plus grand bâtiment du monde (après le Pentagone). Ceaușescu a démoli le vieux Bucarest pour le construire. 1 100 pièces, volume de 3,5M m³. 700 architectes, 20 000 ouvriers. Coût de plusieurs milliards. Aujourd'hui il abrite le parlement et des musées. Monument à l'excès dictatoriale."
        },
        {
          "title": "🧳 Fuite des cerveaux = 5M+ à l'étranger",
          "text": "La Roumanie a perdu plus de 5M de citoyens (25 % de la population) à l'émigration depuis 1990. Médecins, infirmiers, informaticiens, ouvriers du bâtiment sont partis vers l'Europe de l'Ouest. Les villages se vident. Qui soutiendra la Roumanie ? Cet exode est une crise existentielle."
        },
        {
          "title": "🐕 Chiens errants = problème urbain",
          "text": "Bucarest compterait 60 000+ chiens errants (estimations). Des meutes arpentent les rues. Des attaques ont eu lieu (un enfant tué en 2013). Les programmes de stérilisation sont insuffisants. C'est une manifestation visible de la pauvreté et de l'échec des infrastructures. Les visiteurs sont choqués par l'ampleur."
        }
      ]
    }
  }
}