{
  "country": "El Salvador",
  "name_note": "⭐ Expat Score: 5.5 / 10",
  "expat_score": {
    "value": 5.5,
    "max": 10,
    "label": "⭐ Expat Score: 5.5 / 10"
  },
  "snapshot": {
    "capital": "San Salvador",
    "population": "~6.5M",
    "languages": "Spanish",
    "driving_side": "Right"
  },
  "currency": {
    "name": "US dollar (USD) / Bitcoin (BTC)",
    "rate": "1 USD = 1 USD",
    "note": "Uses USD since 2001. Bitcoin became legal tender in 2021 (controversial). Dual currency system."
  },
  "crypto": {
    "friendly": "Yes",
    "note": "Bitcoin is legal tender since 2021 under President Bukele. Government promotes crypto adoption. Chivo wallet launched. However, actual usage remains limited."
  },
  "article": "🧭 **Overview**\nEl Salvador is Central America's smallest and most densely populated country, historically known for gang violence (MS-13, Barrio 18) and civil war (1980-92). President Nayib Bukele (since 2019) implemented controversial policies: mass gang roundups (60,000+ arrested), state of emergency suspending rights, and Bitcoin legal tender adoption. Security has improved dramatically but at cost of human rights. The country uses USD since 2001. San Salvador is the capital; beach towns (El Tunco, El Zonte) attract surfers and crypto enthusiasts. The economy relies on remittances (25% of GDP), agriculture, and growing tourism. Volcanoes, beaches, and surf draw visitors.\n\n👥 **People & vibe**\nWith roughly 6.5 million people (plus 2.5M+ in US diaspora), El Salvador is predominantly mestizo (~86%) with smaller white and indigenous populations. Spanish is the language. The culture is shaped by civil war trauma, gang violence legacy, and massive emigration. Family ties are strong despite geographic separation. Salvadorans (Salvadoreños) are entrepreneurial and resilient. The vibe has shifted under Bukele — from fear of gangs to cautious optimism mixed with concerns about authoritarianism. San Salvador is urban and business-focused; coast is laid-back surf culture; rural areas remain traditional.\n\n[[MAP]]\n\n🌦️ **Climate & landscape**\nExpect tropical climate: hot year-round (25-32°C) with rainy season (May-October) and dry season (November-April). Pacific coast is hot; mountains are cooler. The landscape includes Pacific beaches (black volcanic sand), volcanic chain (20+ volcanoes, some active like Santa Ana), mountains, and lakes (Coatepeque). Natural beauty is compact and accessible. The country is mountainous and prone to earthquakes. Air quality in San Salvador can be poor.\n\n🏠 **Housing & settling in**\nSan Salvador neighborhoods like Escalón, Santa Elena, and San Benito attract expats and wealthy Salvadorans. Coastal towns (El Tunco, El Zonte, La Libertad) have growing expat/digital nomad presence. Expect 1-2 months deposit and 6-12 month contracts. Rents are moderate: $400-1,000/month. Quality varies — modern apartments in gated communities vs. basic housing. Security is important — walls, guards. Outside capital and coast, options are limited. Buying property is allowed. Registration is required.\n\n💼 **Work & economy**\nThe economy is remittance-dependent (25% GDP from diaspora), with manufacturing (maquiladoras), agriculture (coffee), and growing tourism/crypto sectors. For foreigners, opportunities are limited to teaching English, NGO work, crypto businesses, or remote work. Work permits require employer sponsorship. Salaries are low ($300-800/month average locally). Many expats work remotely or are Bitcoin entrepreneurs. Starting a business is feasible but bureaucratic. Recent Bitcoin adoption created crypto tourism but practical adoption is limited. Spanish fluency essential.\n\n🛂 **Visa & entry**\nMost nationalities get 90-day tourist visa on arrival. CA-4 agreement allows movement between El Salvador, Guatemala, Honduras, Nicaragua for 90 days total. For longer stays, options include temporary residence (investor, retiree, family) or work visa. The process is bureaucratic. Permanent residence possible after temporary period. Citizenship requires 5 years residence plus Spanish test. System is manageable but slow. Border runs are common.\n\n🏥 **Healthcare**\nHealthcare has public (overcrowded, under-resourced) and private systems. Private hospitals in San Salvador offer decent care at affordable prices (much cheaper than US). International insurance or local private plans recommended. Medical tourism to nearby Guatemala or Mexico is common for serious procedures. Tropical diseases (dengue, Zika) are risks. Life expectancy is ~74 years. Dental care is affordable. Water quality is poor — bottled water essential.\n\n🚗 **Transport & mobility**\nSan Salvador has buses (often crowded, some unsafe). Most expats drive or use Uber. Traffic in capital is congested but manageable. Roads vary from decent highways to rough rural tracks. Intercity buses connect towns affordably. The country is small — coast to capital is 1 hour. Domestic flights don't exist. Monseñor Óscar Arnulfo Romero International Airport connects to US, Central America, and Mexico. Public transport security has improved under Bukele but caution advised.\n\n🍛 **Food note (national dish)**\nThe national dish is **Pupusas**: thick corn tortillas stuffed with cheese, beans, pork (chicharrón), or loroco (edible flower), served with curtido (cabbage slaw) and tomato salsa. They're ubiquitous, cheap ($0.50-1 each), and central to Salvadoran identity. Pupuserías are everywhere. It's comfort food and source of national pride.\n\n🔎 **Bottom line**\nEl Salvador suits Bitcoin enthusiasts, surfers (great waves), digital nomads seeking affordability, and adventurous types comfortable with developing country realities. Bukele's security crackdown dramatically reduced gang violence (homicide rate dropped 70%+), making it safer than past reputation suggests. However, authoritarianism (mass arrests without due process, press restrictions) creates concerns. Pros: improved security, USD economy, Bitcoin innovation, surf, compact size, cheap. Cons: authoritarian turn, limited economy, poverty, water/electricity issues, and human rights concerns. It's controversial experiment — safer but less free. Best for those accepting trade-offs. Spanish essential.\n\nExpat Score — 5.5 / 10",
  "goDeeper": {
    "national_dish": {
      "name": "Pupusas",
      "note": "Thick corn tortillas stuffed with cheese, beans, or pork, served with curtido and salsa — ubiquitous, cheap, national pride."
    },
    "lgbt_acceptance": {
      "level": "Low",
      "note": "Homosexuality is legal but social attitudes are conservative. Discrimination common. No legal recognition of same-sex relationships. Violence against LGBTQ+ people occurs. Discretion advised."
    },
    "top_sectors": [
      "Remittances from diaspora",
      "Manufacturing (textiles, maquiladoras)",
      "Agriculture (coffee)"
    ],
    "things_to_know": {
      "personality": {
        "name": "Óscar Romero",
        "era": "20th century",
        "story": "Archbishop assassinated in 1980 while saying mass for speaking against government violence during civil war. Martyr and symbol of justice. Canonized by Catholic Church in 2018. His legacy inspires human rights advocacy."
      },
      "cards": [
        {
          "title": "₿ Bitcoin country = experiment",
          "text": "In 2021, Bukele made Bitcoin legal tender — first country to do so. Government bought BTC, built 'Bitcoin Beach' in El Zonte, launched Chivo wallet. It's controversial: adoption is limited, critics call it publicity stunt, IMF disapproves. Crypto tourists visit but locals use USD."
        },
        {
          "title": "🔒 Security improved, rights suspended",
          "text": "Bukele's gang crackdown arrested 60,000+ suspected gang members (2% of population). Homicide rate dropped 70%+. Streets are safer. But state of emergency suspended constitutional rights, prisons are hellish, innocent people arrested. It's security vs freedom trade-off."
        },
        {
          "title": "📱 Bukele = millennial autocrat",
          "text": "Young (43), social media-savvy president who posts memes, wears baseball cap backwards, and calls himself 'world's coolest dictator' (ironically?). Hugely popular domestically (90%+ approval) but concerning to human rights groups. He's rewriting rulebook."
        },
        {
          "title": "🌊 Surf culture thrives",
          "text": "El Salvador has world-class surf breaks. El Tunco, El Zonte, Punta Roca attract international surfers. Surf tourism growing. Bitcoin Beach (El Zonte) combines crypto and surf culture. It's becoming Central American surf destination."
        },
        {
          "title": "💔 Civil war scars remain",
          "text": "1980-92 civil war killed 75,000+, created guerrillas vs government dichotomy, and drove mass emigration. Gang violence that followed was partly consequence of deporting gang members from LA back to war-torn country. Trauma shapes politics and society."
        },
        {
          "title": "🏛️ Remittances = economic lifeline",
          "text": "25% of GDP comes from remittances sent by Salvadorans in US. This creates dependency and ties economy to US. When US sneezes, El Salvador catches pneumonia. Bukele's Bitcoin push partly aims to reduce remittance costs."
        }
      ]
    }
  }
}