{
  "country": "Guatemala",
  "name_note": "⭐ Expat Score: 6.0 / 10",
  "expat_score": {
    "value": 6.0,
    "max": 10,
    "label": "⭐ Expat Score: 6.0 / 10"
  },
  "snapshot": {
    "capital": "Guatemala City",
    "population": "~18M",
    "languages": "Spanish, 21 Mayan languages",
    "driving_side": "Right"
  },
  "currency": {
    "name": "Guatemalan quetzal (GTQ)",
    "rate": "1 USD ≈ 7.80 GTQ",
    "note": "Relatively stable currency. USD widely accepted in tourist areas and for major transactions."
  },
  "crypto": {
    "friendly": "Limited",
    "note": "No specific regulations. Growing interest but limited infrastructure. Legal status unclear but not prohibited."
  },
  "article": "🧭 **Overview**\nGuatemala is the most populous Central American nation, offering ancient Mayan ruins (Tikal), colonial architecture (Antigua), volcanic landscapes (Lake Atitlán), and rich indigenous culture. However, it's also marked by inequality, violence (gang crime, especially in Guatemala City), and 36-year civil war legacy (1960-96, 200,000+ killed). The economy relies on agriculture (coffee, sugar, bananas), remittances (15% of GDP), and growing tourism. Antigua and Lake Atitlán attract expats and digital nomads seeking Spanish immersion, affordability, and natural beauty. Guatemala City is dangerous; tourist areas are safer but require vigilance.\n\n👥 **People & vibe**\nWith roughly 18 million people, Guatemala has largest indigenous population in Central America (~40% Maya, 60% mestizo/ladino). 21 Mayan languages are spoken alongside Spanish. The culture is deeply indigenous-influenced — colorful textiles, markets, traditional dress. Guatemalans are generally friendly but reserved initially. Indigenous-ladino divide is significant. The vibe varies: Guatemala City is dangerous urban sprawl; Antigua is colonial charm; Lake Atitlán is hippie/expat haven; highlands are traditional Maya villages. Civil war trauma lingers. Corruption is endemic.\n\n[[MAP]]\n\n🌦️ **Climate & landscape**\nClimate varies by altitude: tropical lowlands (Petén jungle, Tikal) are hot/humid; highlands (Antigua, Lake Atitlán) have eternal spring (15-25°C); Pacific coast is hot. Rainy season May-October. The landscape is volcanic — 30+ volcanoes (3 active), Lake Atitlán in volcanic caldera, cloud forests, jungle, and Pacific/Caribbean coasts. Natural beauty is stunning and diverse. Earthquakes are frequent. Air quality in Guatemala City is poor.\n\n🏠 **Housing & settling in**\nAntigua and Lake Atitlán (Panajachel, San Marcos, San Pedro) are popular expat bases. Expect 1-2 months deposit and 6-12 month contracts. Rents are cheap: $300-700/month for nice places. Quality varies — colonial houses are charming but may lack amenities; modern places are comfortable. Antigua has earthquake risk; Lake Atitlán has limited services. Guatemala City is avoided by most expats. Buying property is possible but legal protections are weak. Security (walls, guards) is important.\n\n💼 **Work & economy**\nThe economy is agriculture-based (coffee, sugar, cardamom), with remittances, textiles, and tourism. For foreigners, opportunities are limited to teaching English, NGO work, tourism, or remote work. Work permits are difficult and rarely pursued. Many expats work remotely or teach English unofficially. Salaries are very low locally (Q3,000-6,000/month, $400-800). Starting a business is feasible but bureaucratic and corruption affects dealings. Spanish proficiency is essential. Economic inequality is stark.\n\n🛂 **Visa & entry**\nMost nationalities get 90-day tourist visa on arrival. CA-4 agreement allows movement between Guatemala, El Salvador, Honduras, Nicaragua for 90 days total. For longer stays, options include temporary residence (rentista, pensionado, investor) or work visa. The process is bureaucratic and slow. Border runs (leaving CA-4 then re-entering) are common workaround though technically not allowed. Permanent residence possible after temporary period. Citizenship requires 5 years residence plus Spanish test.\n\n🏥 **Healthcare**\nHealthcare is poor in public system — overcrowded, under-resourced. Private hospitals in Guatemala City and Antigua offer decent care at very affordable prices. Serious conditions often require travel to Mexico or US. Medical tourism is growing (especially dentistry). Tropical diseases (dengue, Zika) are risks. Life expectancy is ~75 years. International health insurance recommended. Water quality is poor — bottled water essential.\n\n🚗 **Transport & mobility**\nGuatemala City has red buses (dangerous, avoid) and Transmetro (safer BRT). Antigua has tuk-tuks and shuttles. Lake Atitlán has boat lanchas between villages. Intercity chicken buses (old US school buses) are colorful, cheap, crowded, and sometimes dangerous. Shuttle services connect tourist areas safely. Roads vary from decent highways to dangerous mountain passes. Driving is chaotic. Guatemala City airport connects to US, Mexico, Central America. Domestic flights to Flores (Tikal) available.\n\n🍛 **Food note (national dish)**\nThe national dish is **Pepián**: meat stew (chicken, beef, or pork) with roasted vegetables, seeds, and spices creating thick, complex sauce. It's pre-Columbian Maya dish representing indigenous culinary heritage. Alternatively, **Kak'ik** (turkey soup) from Cobán. Street food includes tostadas, tamales, and elotes (corn). Guatemalan food is corn-based and flavorful.\n\n🔎 **Bottom line**\nGuatemala suits Spanish learners (immersion schools abound), budget travelers, digital nomads, retirees seeking affordability, and those drawn to Mayan culture. Pros: very affordable, stunning natural beauty (volcanoes, lakes, jungle), rich indigenous culture, colonial Antigua charm, and improving infrastructure in tourist areas. Cons: high crime (especially Guatemala City), gang violence, corruption, inequality, and weak rule of law. Antigua and Lake Atitlán are relatively safe but require vigilance. Civil war legacy and ongoing violence create instability. Best for those comfortable with developing country realities and prioritizing affordability and culture over safety and infrastructure. Spanish essential. Security awareness mandatory.\n\nExpat Score — 6.0 / 10",
  "goDeeper": {
    "national_dish": {
      "name": "Pepián",
      "note": "Complex meat stew with seeds and roasted vegetables — pre-Columbian Maya dish representing indigenous heritage. Or Kak'ik (turkey soup)."
    },
    "lgbt_acceptance": {
      "level": "Low",
      "note": "Homosexuality is legal but social attitudes are conservative. Discrimination common. No legal recognition of relationships. Violence against LGBTQ+ people occurs. Discretion advised."
    },
    "top_sectors": [
      "Agriculture (coffee, sugar, cardamom)",
      "Remittances from diaspora",
      "Tourism (Mayan ruins, Antigua)"
    ],
    "things_to_know": {
      "personality": {
        "name": "Rigoberta Menchú",
        "era": "20th-21st century",
        "story": "Indigenous K'iche' Maya activist who won 1992 Nobel Peace Prize for work on indigenous rights and social justice. Her autobiography exposed civil war atrocities against Maya. Controversial figure but symbol of indigenous resistance."
      },
      "cards": [
        {
          "title": "🏛️ Tikal = lost Maya city",
          "text": "Tikal ruins in Petén jungle are among most impressive Maya sites — towering pyramids emerging from rainforest. UNESCO site. Sunrise from Temple IV is bucket list moment. However, it's remote (1-hour flight or 8-hour bus from Antigua). The Maya civilization's sophistication is profound."
        },
        {
          "title": "🌋 Lake Atitlán = volcanic paradise",
          "text": "Lake in volcanic caldera surrounded by three volcanoes, ringed by Maya villages. It's stunning but also overtourism challenge. Villages like San Marcos attract yoga/wellness crowd; San Pedro is backpacker party; Panajachel is commercial. Water quality is declining."
        },
        {
          "title": "⚠️ Guatemala City = avoid",
          "text": "Capital is one of Latin America's most dangerous cities. Zones 1, 3, 6, 12, 18 are particularly dangerous. Gang violence, theft, kidnapping are real risks. Most expats avoid living there. Zone 10 (Zona Viva) is safer but still requires vigilance."
        },
        {
          "title": "💔 Civil war trauma persists",
          "text": "1960-96 civil war killed 200,000+, mostly indigenous Maya. Army committed genocide. Truth commission documented atrocities. Reconciliation is incomplete. Former president Ríos Montt was convicted of genocide then acquitted on technicality. The wounds are fresh."
        },
        {
          "title": "🎨 Indigenous textiles are art",
          "text": "Traditional Maya textiles (huipils, cortes) feature intricate patterns unique to each village. Weaving techniques date back centuries. Chichicastenango market is famous. However, cheap Chinese imports threaten traditional crafts. Authentic textiles are cultural treasures."
        },
        {
          "title": "📚 Spanish schools = industry",
          "text": "Guatemala is top destination for Spanish immersion — particularly Antigua, Lake Atitlán, Quetzaltenango. One-on-one instruction is $5-10/hour. Homestays provide cultural immersion. Quality varies but value is unmatched. Learning Spanish is primary draw for many expats."
        }
      ]
    }
  }
}