{
  "country": "Panama",
  "name_note": "⭐ Expat Score: 7.0 / 10",
  "expat_score": {
    "value": 7.0,
    "max": 10,
    "label": "⭐ Expat Score: 7.0 / 10"
  },
  "snapshot": {
    "capital": "Panama City",
    "population": "~4.4M",
    "languages": "Spanish, English",
    "driving_side": "Right"
  },
  "currency": {
    "name": "US dollar (USD) / Panamanian balboa (PAB)",
    "rate": "1 USD = 1 PAB",
    "note": "Uses US dollar as official currency (since 1904). No exchange rate risk. Balboa coins exist but dollar bills circulate."
  },
  "crypto": {
    "friendly": "Yes",
    "note": "Crypto-friendly. Law recognizes crypto (2021). Growing adoption. El Salvador neighbor influenced policy. Clear regulations developing."
  },
  "article": "🧭 **Overview**\nPanama is a Central American country connecting North and South America, known for Panama Canal (engineering marvel, major revenue source), banking sector (regional financial hub), and biodiversity. Panama City is modern capital with Manhattan-like skyline; Casco Viejo is colonial quarter. The country offers US dollar economy, favorable tax system, retiree programs (Pensionado visa), and strategic location. Economy relies on Canal, banking, logistics, and services. Panama attracts expats and retirees seeking tropical lifestyle with US dollar stability. However, inequality, corruption (Panama Papers 2016), crime, rainy season, and traffic create challenges. It's Central America's economic powerhouse.\n\n👥 **People & vibe**\nWith roughly 4.4 million people, Panama is ethnically diverse: mestizo (~65%), Black/Afro-Panamanian (~15%), white (~10%), indigenous (~7%). Spanish is official; English is spoken (especially in business, Canal Zone legacy). The culture is Latin American with Caribbean and North American influences. Panamanians are friendly, entrepreneurial, and diverse. The vibe is cosmopolitan tropics. Panama City is modern finance hub; Casco Viejo is hipster revival; Bocas del Toro is beach expat haven; interior is rural. Inequality is visible.\n\n[[MAP]]\n\n🌦️ **Climate & landscape**\nExpect tropical climate: hot and humid year-round (25-32°C) with rainy season (May-Nov, heavy afternoon downpours) and dry season (Dec-April). The landscape includes two coastlines (Pacific and Caribbean), mountains (highlands are cooler — Boquete, El Valle), rainforests (Darién is dense jungle), and islands (San Blas, Bocas del Toro). Natural beauty is accessible. Biodiversity is exceptional. Air quality is moderate.\n\n🏠 **Housing & settling in**\nPanama City (Punta Pacifica, Costa del Este, Casco Viejo) attracts expats; Boquete (highlands) and Bocas del Toro (islands) are popular. Expect 1-2 months deposit and annual contracts. Rents: $800-2,000+/month in city; $400-800 in Boquete. Quality is good — modern high-rises in city, houses elsewhere. AC is essential. Outside main areas, options are limited. Buying property is straightforward for foreigners (no restrictions). Registration required. Rainy season flooding can be issue.\n\n💼 **Work & economy**\nThe economy is services-driven: Canal (generates $2.5B+ revenue), banking (regional financial center), logistics (Colón Free Zone), and tourism. For foreigners, opportunities exist in banking, logistics, tech (growing startup scene), tourism, or teaching English. Work permits require employer sponsorship. Pensionado program attracts retirees. Salaries vary: expats earn well ($3k-8k/month); locals earn less. Starting a business is relatively easy. English prevalence (banking, Canal legacy) helps. Territorial tax system (only Panama-sourced income taxed) attracts businesses.\n\n🛂 **Visa & entry**\nMost nationalities get 180-day tourist visa on arrival. For longer stays, options include Friendly Nations visa (citizens of 50 countries can get residence with $5k investment), Pensionado visa (retirees with $1k/month pension get discounts), or work permits. The process is bureaucratic but accessible. Permanent residence leads to citizenship eligibility after 5 years. Naturalization is achievable — requires Spanish proficiency.\n\n🏥 **Healthcare**\nHealthcare is two-tier. Public system (CSS) is affordable but crowded. Private hospitals (Hospital Punta Pacifica, affiliated with Johns Hopkins) offer excellent care at reasonable prices. Medical tourism attracts North Americans (dentistry, cosmetic surgery, procedures). Life expectancy is ~79 years. International insurance or private insurance recommended. Prescription drugs are affordable. Quality in Panama City is good; rural areas are basic.\n\n🚗 **Transport & mobility**\nPanama City has metro (2 lines, expanding), buses, and Uber. Traffic is terrible — congestion, aggressive driving. Most expats drive or use Uber. Roads in cities are decent; Pan-American Highway connects interior. Darién Gap (no road between Panama and Colombia — jungle) is notorious. Domestic flights connect interior and islands. Tocumen International Airport is major hub for Latin America. Regional travel is easy.\n\n🍛 **Food note (national dish)**\nThe national dish is **Sancocho**: chicken soup with yuca, corn, plantains, cilantro. It's comfort food served at family gatherings. Alternatively, **Ceviche** or **Ropa Vieja** (shredded beef). Panamanian cuisine is Latin American with Caribbean influences. Seafood is excellent. International food is widely available in Panama City.\n\n🔎 **Bottom line**\nPanama suits retirees (Pensionado program offers discounts), digital nomads, expats seeking Latin America with US dollar stability, families, and investors. Pros: US dollar (no currency risk), Canal revenue creates wealth, banking hub, strategic location, biodiversity, Friendly Nations and Pensionado visa programs, and improving infrastructure. Cons: inequality (stark), corruption (Panama Papers exposed offshore industry), crime (especially Panama City), traffic chaos, rainy season (6+ months), and hot/humid climate. Panama City is modern but congested; Boquete offers mountain escape; beaches attract tourists. Best for those seeking tropical Latin American lifestyle with dollar stability and willing to accept inequality and corruption. Spanish essential for integration. If you want Central America's most developed economy with mountains, beaches, and no currency risk, Panama delivers.\n\nExpat Score — 7.0 / 10",
  "goDeeper": {
    "national_dish": {
      "name": "Sancocho / Ceviche",
      "note": "Chicken soup with yuca or ceviche — Latin American/Caribbean cuisine. Seafood is excellent. International food widely available."
    },
    "lgbt_acceptance": {
      "level": "Moderate",
      "note": "Homosexuality is legal. Social attitudes are improving, especially in Panama City. No same-sex marriage but some protections. Panama City has LGBTQ+ scene. More accepting than regional neighbors."
    },
    "top_sectors": [
      "Panama Canal operations",
      "Banking & financial services",
      "Logistics & free trade zone"
    ],
    "things_to_know": {
      "personality": {
        "name": "Omar Torrijos",
        "era": "20th century",
        "story": "Military leader (1968-81) who negotiated Torrijos-Carter Treaties (1977) transferring Canal from US to Panama (completed 1999). Populist dictator who improved rural infrastructure. Died in plane crash (1981). National hero for Canal sovereignty."
      },
      "cards": [
        {
          "title": "🚢 Panama Canal = economic lifeline",
          "text": "Connects Atlantic and Pacific, handles 6% of world trade. Generates $2.5B+ revenue annually. Expanded in 2016 to handle Neopanamax ships. It's economic foundation and national pride. US controlled 1904-99; Panama took over. Revenue funds development."
        },
        {
          "title": "💼 Panama Papers (2016) = offshore capital",
          "text": "Massive leak exposed Panama's offshore banking industry — shell companies, tax evasion, money laundering for global elite. Mossack Fonseca law firm at center. It confirmed Panama's role as financial secrecy jurisdiction. Reputation damaged but industry continues."
        },
        {
          "title": "🏖️ Bocas del Toro = expat island life",
          "text": "Caribbean islands with beaches, diving, reggae vibe. Popular with backpackers, expats, retirees. Cost of living lower than city. However, tourism strain and overdevelopment threaten character. Power cuts, water issues are common. It's laid-back tropical escape."
        },
        {
          "title": "🏔️ Boquete = mountain retiree haven",
          "text": "Highland town (1,200m altitude) with eternal spring climate, coffee plantations, and large expat community (especially North American retirees). Pensionado visa offers discounts (25% off restaurants, 50% off entertainment). It's Panama's top expat destination outside city."
        },
        {
          "title": "🌳 Darién Gap = impenetrable jungle",
          "text": "100km of roadless jungle between Panama and Colombia — only break in Pan-American Highway (Alaska to Argentina). Dense rainforest, swamps, dangerous. Migrants trying to reach US traverse it (many die). It's one of world's most dangerous jungles. No infrastructure."
        },
        {
          "title": "💵 USD economy = stability",
          "text": "Panama uses US dollar since 1904 (no central bank, no monetary policy). This creates price stability, attracts investment, but also means no ability to devalue during crisis. It's rare for non-US territory. The dollar is both benefit and constraint."
        }
      ]
    }
  }
}